tospy/__init__.py
tospy-0.1.0.dist-info/WHEEL
tospy-0.1.0.dist-info/METADATA
tospy-0.1.0.dist-info/RECORD
