Metadata-Version: 2.1
Name: tospy
Version: 0.1.0
Summary: 
Author: Nick Bean
Author-email: nickbean2255@yahoo.com
Requires-Python: >=3.9,<4.0
Classifier: Programming Language :: Python :: 3
Classifier: Programming Language :: Python :: 3.9
Requires-Dist: requests (>=2.25.1,<3.0.0)
